[{"image": "07_missing_hole_02.jpg", "annotations": [{"label": "hole_ok", "coordinates": {"x": 347.0000000000002, "y": 1306.0, "width": 135.00000000000006, "height": 121.0}}, {"label": "hole_ok", "coordinates": {"x": 205.00000000000017, "y": 1209.0, "width": 135.00000000000009, "height": 121.0}}, {"label": "hole_ok", "coordinates": {"x": 885.5000000000001, "y": 1491.5, "width": 84.0, "height": 100.0}}, {"label": "hole_ok", "coordinates": {"x": 958.5, "y": 1485.5, "width": 83.99999999999989, "height": 100.0}}, {"label": "hole_ok", "coordinates": {"x": 1021.5000000000001, "y": 1495.5, "width": 83.99999999999977, "height": 100.0}}, {"label": "hole_ok", "coordinates": {"x": 1092.5, "y": 1491.5, "width": 83.99999999999977, "height": 100.0}}, {"label": "hole_ok", "coordinates": {"x": 1163.5, "y": 1493.5, "width": 83.99999999999977, "height": 100.0}}, {"label": "hole_ok", "coordinates": {"x": 1231.5, "y": 1493.5, "width": 83.99999999999977, "height": 100.0}}, {"label": "hole_ok", "coordinates": {"x": 1304.5, "y": 1493.5, "width": 83.99999999999977, "height": 100.0}}, {"label": "hole_ok", "coordinates": {"x": 1371.5, "y": 1491.5, "width": 83.99999999999977, "height": 100.0}}, {"label": "hole_ok", "coordinates": {"x": 1442.5, "y": 1490.5, "width": 83.99999999999977, "height": 100.0}}, {"label": "hole_ok", "coordinates": {"x": 1510.5, "y": 1494.5, "width": 83.99999999999977, "height": 100.0}}, {"label": "hole_ok", "coordinates": {"x": 1653.5, "y": 1492.5, "width": 83.99999999999977, "height": 100.0}}, {"label": "hole_ok", "coordinates": {"x": 1725.5, "y": 1492.5, "width": 83.99999999999977, "height": 100.0}}, {"label": "hole_ok", "coordinates": {"x": 1792.5, "y": 1492.5, "width": 83.99999999999977, "height": 100.0}}, {"label": "hole_ok", "coordinates": {"x": 1858.5, "y": 1492.5, "width": 83.99999999999977, "height": 100.0}}, {"label": "hole_ok", "coordinates": {"x": 1927.5, "y": 1488.5, "width": 83.99999999999977, "height": 100.0}}, {"label": "hole_ok", "coordinates": {"x": 1998.5, "y": 1490.5, "width": 83.99999999999977, "height": 100.0}}, {"label": "hole_ok", "coordinates": {"x": 2069.5, "y": 1493.5, "width": 84.0, "height": 100.0}}, {"label": "hole_ok", "coordinates": {"x": 2136.5, "y": 1493.5, "width": 84.0, "height": 100.0}}, {"label": "hole_ok", "coordinates": {"x": 2211.5, "y": 1495.5, "width": 84.0, "height": 100.0}}, {"label": "hole_ok", "coordinates": {"x": 882.5, "y": 1070.5, "width": 83.99999999999977, "height": 100.0}}, {"label": "hole_ok", "coordinates": {"x": 961.5, "y": 1070.5, "width": 83.99999999999977, "height": 100.0}}, {"label": "hole_ok", "coordinates": {"x": 1026.5, "y": 1070.5, "width": 83.99999999999977, "height": 100.0}}, {"label": "hole_ok", "coordinates": {"x": 1097.5, "y": 1070.5, "width": 83.99999999999977, "height": 100.0}}, {"label": "hole_ok", "coordinates": {"x": 1164.5, "y": 1070.5, "width": 83.99999999999977, "height": 100.0}}, {"label": "hole_ok", "coordinates": {"x": 1301.5, "y": 1068.5, "width": 83.99999999999977, "height": 100.0}}, {"label": "hole_ok", "coordinates": {"x": 1376.5, "y": 1072.5, "width": 83.99999999999977, "height": 100.0}}, {"label": "hole_ok", "coordinates": {"x": 1444.5, "y": 1072.5, "width": 83.99999999999977, "height": 100.0}}, {"label": "hole_ok", "coordinates": {"x": 1513.5, "y": 1070.5, "width": 83.99999999999977, "height": 100.0}}, {"label": "hole_ok", "coordinates": {"x": 1582.5, "y": 1070.5, "width": 83.99999999999977, "height": 100.0}}, {"label": "hole_ok", "coordinates": {"x": 1647.5, "y": 1071.5, "width": 83.99999999999977, "height": 100.0}}, {"label": "hole_ok", "coordinates": {"x": 1720.5, "y": 1071.5, "width": 83.99999999999977, "height": 100.0}}, {"label": "hole_ok", "coordinates": {"x": 1789.5, "y": 1073.5, "width": 83.99999999999977, "height": 100.0}}, {"label": "hole_ok", "coordinates": {"x": 1866.5, "y": 1073.5, "width": 83.99999999999977, "height": 100.0}}, {"label": "hole_ok", "coordinates": {"x": 1934.5, "y": 1071.5, "width": 83.99999999999977, "height": 100.0}}, {"label": "hole_ok", "coordinates": {"x": 2005.5, "y": 1075.5, "width": 83.99999999999977, "height": 100.0}}, {"label": "hole_ok", "coordinates": {"x": 2074.5, "y": 1073.5, "width": 84.0, "height": 100.0}}, {"label": "hole_ok", "coordinates": {"x": 2151.5, "y": 1077.5, "width": 84.0, "height": 100.0}}, {"label": "hole_ok", "coordinates": {"x": 2221.5, "y": 1075.5, "width": 84.0, "height": 100.0}}, {"label": "hole_ok", "coordinates": {"x": 2149.5, "y": 767.5, "width": 84.0, "height": 99.99999999999989}}, {"label": "hole_ok", "coordinates": {"x": 2218.5, "y": 771.5, "width": 84.0, "height": 99.99999999999989}}, {"label": "hole_ok", "coordinates": {"x": 2295.5, "y": 765.5, "width": 84.0, "height": 99.99999999999989}}, {"label": "hole_ok", "coordinates": {"x": 2489.5, "y": 817.5, "width": 84.0, "height": 99.99999999999989}}, {"label": "hole_ok", "coordinates": {"x": 2714.5, "y": 817.5, "width": 84.0, "height": 99.99999999999989}}, {"label": "hole_ok", "coordinates": {"x": 2491.5, "y": 394.5, "width": 84.0, "height": 99.99999999999994}}, {"label": "hole_ok", "coordinates": {"x": 471.5000000000001, "y": 342.00000000000006, "width": 97.99999999999994, "height": 87.0}}, {"label": "hole_ok", "coordinates": {"x": 612.5, "y": 348.00000000000006, "width": 97.99999999999989, "height": 87.0}}, {"label": "hole_ok", "coordinates": {"x": 464.5000000000001, "y": 592.0, "width": 97.99999999999983, "height": 86.99999999999989}}, {"label": "hole_ok", "coordinates": {"x": 473.5000000000001, "y": 738.0, "width": 97.99999999999983, "height": 86.99999999999989}}, {"label": "hole_ok", "coordinates": {"x": 606.5, "y": 736.0, "width": 97.99999999999989, "height": 86.99999999999989}}, {"label": "hole_ok", "coordinates": {"x": 604.5, "y": 598.0, "width": 97.99999999999989, "height": 86.99999999999989}}, {"label": "hole_ok", "coordinates": {"x": 704.5, "y": 590.0, "width": 97.99999999999989, "height": 86.99999999999989}}, {"label": "hole_ok", "coordinates": {"x": 800.5, "y": 598.0, "width": 97.99999999999989, "height": 86.99999999999989}}, {"label": "hole_ok", "coordinates": {"x": 839.5, "y": 334.0, "width": 97.99999999999989, "height": 86.99999999999989}}, {"label": "hole_ok", "coordinates": {"x": 914.5, "y": 334.0, "width": 97.99999999999989, "height": 86.99999999999989}}, {"label": "hole_ok", "coordinates": {"x": 988.5, "y": 334.0, "width": 97.99999999999989, "height": 86.99999999999989}}, {"label": "hole_ok", "coordinates": {"x": 1223.5, "y": 305.0, "width": 97.99999999999977, "height": 86.99999999999989}}, {"label": "hole_ok", "coordinates": {"x": 1334.5, "y": 305.0, "width": 97.99999999999977, "height": 86.99999999999989}}, {"label": "hole_ok", "coordinates": {"x": 1457.5, "y": 284.0, "width": 97.99999999999977, "height": 86.99999999999989}}, {"label": "hole_ok", "coordinates": {"x": 1463.5, "y": 203.0, "width": 97.99999999999977, "height": 86.99999999999989}}, {"label": "hole_ok", "coordinates": {"x": 1463.5, "y": 380.0, "width": 97.99999999999977, "height": 86.99999999999989}}, {"label": "hole_ok", "coordinates": {"x": 1154.5, "y": 415.0, "width": 97.99999999999977, "height": 86.99999999999989}}, {"label": "hole_ok", "coordinates": {"x": 1275.5, "y": 563.0, "width": 97.99999999999977, "height": 86.99999999999989}}, {"label": "hole_ok", "coordinates": {"x": 1352.5, "y": 561.0, "width": 97.99999999999977, "height": 86.99999999999989}}, {"label": "hole_ok", "coordinates": {"x": 1419.5, "y": 556.0, "width": 97.99999999999977, "height": 86.99999999999989}}, {"label": "hole_ok", "coordinates": {"x": 1494.5, "y": 556.0, "width": 97.99999999999977, "height": 86.99999999999989}}, {"label": "hole_ok", "coordinates": {"x": 1646.5, "y": 555.0, "width": 97.99999999999977, "height": 86.99999999999989}}, {"label": "hole_ok", "coordinates": {"x": 1725.5, "y": 555.0, "width": 97.99999999999977, "height": 86.99999999999989}}, {"label": "hole_ok", "coordinates": {"x": 1796.5, "y": 555.0, "width": 97.99999999999977, "height": 86.99999999999989}}, {"label": "hole_ok", "coordinates": {"x": 1875.5, "y": 561.0, "width": 97.99999999999977, "height": 86.99999999999989}}, {"label": "hole_ok", "coordinates": {"x": 1896.5, "y": 315.0, "width": 97.99999999999977, "height": 86.99999999999994}}, {"label": "hole_ok", "coordinates": {"x": 1896.5, "y": 413.0, "width": 97.99999999999977, "height": 86.99999999999994}}, {"label": "hole_ok", "coordinates": {"x": 1894.5, "y": 480.0, "width": 97.99999999999977, "height": 86.99999999999994}}, {"label": "hole_ok", "coordinates": {"x": 2000.5, "y": 335.0, "width": 97.99999999999977, "height": 86.99999999999994}}, {"label": "hole_ok", "coordinates": {"x": 2085.5, "y": 331.0, "width": 98.0, "height": 86.99999999999994}}, {"label": "hole_ok", "coordinates": {"x": 2164.5, "y": 331.0, "width": 98.0, "height": 86.99999999999994}}, {"label": "hole_ok", "coordinates": {"x": 2246.5, "y": 338.0, "width": 98.0, "height": 86.99999999999994}}, {"label": "hole_ok", "coordinates": {"x": 2358.5, "y": 371.0, "width": 98.0, "height": 86.99999999999994}}, {"label": "hole_ok", "coordinates": {"x": 2063.5, "y": 446.0, "width": 98.0, "height": 86.99999999999994}}, {"label": "hole_ok", "coordinates": {"x": 2223.5, "y": 444.0, "width": 98.0, "height": 86.99999999999994}}, {"label": "hole_ok", "coordinates": {"x": 1277.5, "y": 768.5, "width": 83.99999999999977, "height": 99.99999999999989}}, {"label": "hole_ok", "coordinates": {"x": 1352.5, "y": 766.5, "width": 83.99999999999977, "height": 99.99999999999989}}, {"label": "hole_ok", "coordinates": {"x": 1123.5, "y": 789.5, "width": 83.99999999999977, "height": 99.99999999999989}}, {"label": "hole_ok", "coordinates": {"x": 2073.5, "y": 560.5, "width": 84.0, "height": 99.99999999999989}}, {"label": "hole_ok", "coordinates": {"x": 2150.5, "y": 563.5, "width": 84.0, "height": 99.99999999999989}}, {"label": "hole_ok", "coordinates": {"x": 2219.5, "y": 557.5, "width": 84.0, "height": 99.99999999999989}}, {"label": "hole_ok", "coordinates": {"x": 2294.5, "y": 557.5, "width": 84.0, "height": 99.99999999999989}}, {"label": "hole_ok", "coordinates": {"x": 2716.5, "y": 395.5, "width": 84.0, "height": 99.99999999999994}}, {"label": "hole_ok", "coordinates": {"x": 2714.5, "y": 393.5, "width": 84.0, "height": 99.99999999999994}}, {"label": "hole_ok", "coordinates": {"x": 2360.5, "y": 284.0, "width": 98.0, "height": 86.99999999999994}}, {"label": "hole_ok", "coordinates": {"x": 2358.5, "y": 282.0, "width": 98.0, "height": 86.99999999999994}}, {"label": "hole_ok", "coordinates": {"x": 1686.5, "y": 462.0, "width": 97.99999999999977, "height": 86.99999999999994}}, {"label": "hole_ok", "coordinates": {"x": 778.0000000000001, "y": 790.0000000000001, "width": 69.0, "height": 67.0}}, {"label": "hole_ok", "coordinates": {"x": 843.0000000000001, "y": 788.0000000000001, "width": 69.0, "height": 67.0}}, {"label": "hole_ok", "coordinates": {"x": 918.0000000000001, "y": 795.0000000000001, "width": 69.0, "height": 67.0}}, {"label": "hole_ok", "coordinates": {"x": 982.0000000000001, "y": 797.0000000000001, "width": 69.0, "height": 67.0}}, {"label": "hole_ok", "coordinates": {"x": 1057.0, "y": 801.0000000000001, "width": 68.99999999999977, "height": 67.0}}, {"label": "hole_ok", "coordinates": {"x": 1418.0, "y": 768.0000000000001, "width": 68.99999999999977, "height": 67.0}}, {"label": "hole_ok", "coordinates": {"x": 1489.0, "y": 768.0000000000001, "width": 68.99999999999977, "height": 67.0}}, {"label": "hole_ok", "coordinates": {"x": 1793.0, "y": 776.0000000000001, "width": 68.99999999999977, "height": 67.0}}, {"label": "hole_ok", "coordinates": {"x": 1872.0, "y": 768.0000000000001, "width": 68.99999999999977, "height": 67.0}}, {"label": "hole_ok", "coordinates": {"x": 2074.0, "y": 768.0000000000001, "width": 69.0, "height": 67.0}}, {"label": "hole_ok", "coordinates": {"x": 1652.5, "y": 768.5, "width": 83.99999999999977, "height": 99.99999999999989}}, {"label": "hole_ok", "coordinates": {"x": 1725.5, "y": 773.5, "width": 83.99999999999977, "height": 99.99999999999989}}, {"label": "hole_not_ok", "coordinates": {"x": 1153.0, "y": 226.00000000000003, "width": 68.99999999999977, "height": 66.99999999999994}}, {"label": "hole_not_ok", "coordinates": {"x": 1586.5, "y": 1491.5, "width": 83.99999999999977, "height": 100.0}}, {"label": "hole_not_ok", "coordinates": {"x": 1240.5, "y": 1071.5, "width": 83.99999999999977, "height": 100.0}}, {"label": "hole_not_ok", "coordinates": {"x": 1743.5000000000002, "y": 376.00000000000006, "width": 90.0, "height": 77.0}}, {"label": "hole_not_ok", "coordinates": {"x": 349.00000000000017, "y": 1125.0, "width": 135.0000000000001, "height": 121.0}}]}]